odoo/addons/sale_blanket_order/README.rst
odoo/addons/sale_blanket_order/__init__.py
odoo/addons/sale_blanket_order/__manifest__.py
odoo/addons/sale_blanket_order/data/ir_cron.xml
odoo/addons/sale_blanket_order/data/sequence.xml
odoo/addons/sale_blanket_order/i18n/de.po
odoo/addons/sale_blanket_order/i18n/sale_blanket_order.pot
odoo/addons/sale_blanket_order/models/__init__.py
odoo/addons/sale_blanket_order/models/blanket_orders.py
odoo/addons/sale_blanket_order/models/sale_config_settings.py
odoo/addons/sale_blanket_order/models/sale_orders.py
odoo/addons/sale_blanket_order/readme/CONTRIBUTORS.rst
odoo/addons/sale_blanket_order/readme/DESCRIPTION.rst
odoo/addons/sale_blanket_order/readme/USAGE.rst
odoo/addons/sale_blanket_order/report/report.xml
odoo/addons/sale_blanket_order/report/templates.xml
odoo/addons/sale_blanket_order/security/ir.model.access.csv
odoo/addons/sale_blanket_order/security/security.xml
odoo/addons/sale_blanket_order/static/description/BO_actions.png
odoo/addons/sale_blanket_order/static/description/BO_form.png
odoo/addons/sale_blanket_order/static/description/BO_lines.png
odoo/addons/sale_blanket_order/static/description/BO_menu.png
odoo/addons/sale_blanket_order/static/description/PO_BOLine.png
odoo/addons/sale_blanket_order/static/description/PO_from_BO.png
odoo/addons/sale_blanket_order/static/description/icon.png
odoo/addons/sale_blanket_order/static/description/index.html
odoo/addons/sale_blanket_order/tests/__init__.py
odoo/addons/sale_blanket_order/tests/test_blanket_orders.py
odoo/addons/sale_blanket_order/tests/test_sale_order.py
odoo/addons/sale_blanket_order/views/sale_blanket_order_views.xml
odoo/addons/sale_blanket_order/views/sale_config_settings.xml
odoo/addons/sale_blanket_order/views/sale_order_views.xml
odoo/addons/sale_blanket_order/wizard/__init__.py
odoo/addons/sale_blanket_order/wizard/create_sale_orders.py
odoo/addons/sale_blanket_order/wizard/create_sale_orders.xml
odoo11_addon_sale_blanket_order-11.0.1.0.2.dist-info/METADATA
odoo11_addon_sale_blanket_order-11.0.1.0.2.dist-info/WHEEL
odoo11_addon_sale_blanket_order-11.0.1.0.2.dist-info/top_level.txt
odoo11_addon_sale_blanket_order-11.0.1.0.2.dist-info/RECORD
